{"run_number": "1713684706120108", "step_name": "generate_embeddings", "task_id": "3", "attempt_id": 0, "name": "df_train", "content_type": "gzip+pickle-v2", "type": "metaflow.artifact", "sha": "1c66c01f8224afb245834ea3c467ee2504c35c20", "ds_type": "local", "location": ":root:/home/shashwat/Desktop/Newest Microservice/.metaflow", "flow_id": "DataFlow", "user_name": "shashwat", "tags": [], "system_tags": ["python_version:3.11.7", "metaflow_version:2.11.10", "user:shashwat", "runtime:dev"], "ts_epoch": 1713684716701}